README.rst
setup.py
pyflect/__init__.py
pyflect.egg-info/PKG-INFO
pyflect.egg-info/SOURCES.txt
pyflect.egg-info/dependency_links.txt
pyflect.egg-info/top_level.txt
pyflect/core/__init__.py
pyflect/core/clonable.py
pyflect/core/reflected.py
pyflect/core/filter/__init__.py
pyflect/core/filter/filter.py
pyflect/core/filter/impl/__init__.py
pyflect/core/filter/impl/basic/__init__.py
pyflect/core/filter/impl/basic/basic.py
pyflect/core/filter/impl/reflect/__init__.py
pyflect/core/filter/impl/reflect/reflect.py
pyflect/core/instor/__init__.py
pyflect/core/instor/instor.py
pyflect/ex/__init__.py
pyflect/util/__init__.py
tests/__init__.py
tests/core/__init__.py
tests/core/core_more_logic_tests.py
tests/core/core_tests.py
tests/filter/__init__.py
tests/filter/filter_tests.py
tests/instor/__init__.py
tests/instor/instor_tests.py