Metadata-Version: 1.1
Name: pyflect
Version: 0.1.3
Summary: Put on your Java suit and go get_methods
Home-page: https://github.com/n9code/pyflect
Author: Bagrat Aznauryan
Author-email: bagrat@aznauryan.org
License: MIT
Download-URL: https://github.com/n9code/pyflect
Keywords: reflection java getmethods getfields
Platform: UNKNOWN
Classifier: License :: OSI Approved :: MIT License
Classifier: Intended Audience :: Developers
Classifier: Natural Language :: English
Classifier: Programming Language :: Python
Classifier: Programming Language :: Python :: 2
Classifier: Programming Language :: Python :: 3
Classifier: Operating System :: POSIX
Classifier: Operating System :: POSIX :: Linux
Classifier: Operating System :: MacOS
Classifier: Operating System :: Microsoft :: Windows
Classifier: Programming Language :: Java
Classifier: Topic :: Software Development :: Libraries :: Python Modules
